README.rst
setup.py
autoload_fixtures/__init__.py
django_autoload_fixtures.egg-info/PKG-INFO
django_autoload_fixtures.egg-info/SOURCES.txt
django_autoload_fixtures.egg-info/dependency_links.txt
django_autoload_fixtures.egg-info/requires.txt
django_autoload_fixtures.egg-info/top_level.txt