Metadata-Version: 1.0
Name: django-autoload-fixtures
Version: 0.2
Summary: This library allows you to load initial Fixtures automagically after the South migrate your Model.
Home-page: https://github.com/luanfonceca/django-autoload-fixtures
Author: Luan Fonseca
Author-email: luanfonceca@gmail.com
License: BSD
Platform: UNKNOWN
Classifier: Development Status :: 3 - Alpha
Classifier: Environment :: Web Environment
Classifier: Framework :: Django
Classifier: Intended Audience :: Developers
Classifier: License :: OSI Approved :: MIT License
Classifier: Natural Language :: English
Classifier: Operating System :: OS Independent
Classifier: Programming Language :: Python
